xtu/network/__init__.py
xtu/network/api.py
xtu/network/api.pyi
xtu/network/const.py
xtu/network/encrypt.py
xtu/network/exception.py
xtu/network/models.py
xtu/network/utils.py
xtu_network-0.0.29.dist-info/METADATA
xtu_network-0.0.29.dist-info/WHEEL
xtu_network-0.0.29.dist-info/top_level.txt
xtu_network-0.0.29.dist-info/RECORD
